{
  "646094411": {
    "message": "fix(deps): update dependency react-hook-form to v7.39.1 (#6786)",
    "needsCherryPick": false
  },
  "88581e17f": {
    "message": "[CRWA]: Switch to using enquirer, add engine compatibility override option (#6723)",
    "needsCherryPick": false
  },
  "28226b5e4": {
    "message": "fix: move hooks after components (#6797)",
    "needsCherryPick": false
  },
  "2ec53b601": {
    "message": "[Tutorial]: Fix Typescript code blocks inconsistency (#6801)",
    "needsCherryPick": false
  },
  "52f3ca42c": {
    "message": "fix(deps): update dependency eslint to v8.26.0 (#6785)",
    "needsCherryPick": false
  },
  "be96b5535": {
    "message": "(docs): Minor Command update about Storybook (#6722)",
    "needsCherryPick": false
  },
  "91ae7b6ac": {
    "message": "docs: Add mocking useLocation to docs (#6791)",
    "needsCherryPick": false
  },
  "97c13754c": {
    "message": "fix(deps): update jest monorepo (#6787)",
    "needsCherryPick": false
  },
  "737ed08ab": {
    "message": "fix: publish canary using premajor (#6794)",
    "needsCherryPick": false
  },
  "7954ef0e3": {
    "message": "chore(deps): update dependency @replayio/playwright to v0.3.2 (#6816)",
    "needsCherryPick": false
  },
  "f00c3eb51": {
    "message": "fix(deps): update dependency fastify-raw-body to v4.1.1 (#6817)",
    "needsCherryPick": false
  },
  "a66a57902": {
    "message": "(crwa): Add git init option (#6805)",
    "needsCherryPick": false
  },
  "45da5f312": {
    "message": "fix(deps): update dependency webpack to v5.75.0 (#6849)",
    "needsCherryPick": false
  },
  "4ef01879d": {
    "message": "fix(deps): update dependency @fastify/http-proxy to v8.3.0 (#6821)",
    "needsCherryPick": false
  },
  "3fa6f8eb8": {
    "message": "docs(tutorial): Fix wrong typing on createContact service (#6810)",
    "needsCherryPick": false
  },
  "87adc34cc": {
    "message": "chore(generate): Refactor how page tests are written  (#6825)",
    "needsCherryPick": false
  },
  "0b83391a0": {
    "message": "docs: Fix capitalization of \"--webauthn\" (#6815)",
    "needsCherryPick": false
  },
  "280119efb": {
    "message": "chore(generate): refactor layout generator tests for performance (#6826)",
    "needsCherryPick": false
  },
  "075aa1e51": {
    "message": "chore(generate): refactor functions generator tests for performance (#6827)",
    "needsCherryPick": false
  },
  "fa61ea5bd": {
    "message": "chore(generate): update scaffoldPath test (#6828)",
    "needsCherryPick": false
  },
  "f22619e87": {
    "message": "fix(deps): update dependency pino to v8.7.0 (#6823)",
    "needsCherryPick": false
  }
}
